TelegramTextApp/TTA.py
TelegramTextApp/__init__.py
TelegramTextApp/config.py
TelegramTextApp/inline_mode.py
TelegramTextApp/setup_menu.py
TelegramTextApp/update_bot.py
TelegramTextApp/utils/__init__.py
TelegramTextApp/utils/database.py
TelegramTextApp/utils/logger.py
TelegramTextApp/utils/utils.py
telegramtextapp-0.7.4.1.dist-info/METADATA
telegramtextapp-0.7.4.1.dist-info/WHEEL
telegramtextapp-0.7.4.1.dist-info/top_level.txt
telegramtextapp-0.7.4.1.dist-info/RECORD
