Metadata-Version: 2.4
Name: TelegramTextApp
Version: 0.7.4.1
Summary: Библиотека для создания текстовых приложений в telegram
Home-page: https://github.com/falbue/TelegramTextApp
Author: falbue
Author-email: cyansair05@gmail.com
Classifier: Programming Language :: Python :: 3
Classifier: License :: OSI Approved :: MIT License
Classifier: Operating System :: OS Independent
Requires-Python: >=3.10
Requires-Dist: aiogram
Requires-Dist: aiohttp
Requires-Dist: aiosqlite
Requires-Dist: asyncio
Requires-Dist: dotenv
Dynamic: author
Dynamic: author-email
Dynamic: classifier
Dynamic: description
Dynamic: description-content-type
Dynamic: home-page
Dynamic: requires-dist
Dynamic: requires-python
Dynamic: summary
